{
  "customizations": {
    "vscode": {
      "extensions": [
        "arrterian.nix-env-selector",
        "esbenp.prettier-vscode",
        "github.vscode-github-actions",
        "golang.go",
        "gruntfuggly.todo-tree",
        "johnpapa.vscode-peacock",
        "kamadorueda.alejandra",
        "mkhl.direnv",
        "ms-azuretools.vscode-docker",
        "ms-kubernetes-tools.vscode-kubernetes-tools",
        "ms-vscode.makefile-tools",
        "nhoizey.gremlins",
        "pinage404.nix-extension-pack",
        "redhat.vscode-yaml",
        "streetsidesoftware.code-spell-checker",
        "tekumura.typos-vscode",
        "timonwong.shellcheck",
        "tuxtina.json2yaml",
        "hediet.vscode-drawio",
        "vscodevim.vim",
        "wakatime.vscode-wakatime",
        "yzhang.markdown-all-in-one"
      ]
    }
  },
  "image": "ghcr.io/cachix/devenv:latest",
  "overrideCommand": false,
  "updateContentCommand": "devenv test"
}
